{
  "level": 5,
  "module": "IT Vocabulary Bank (1000 Words)",
  "title": "Version Control & Git - 50 Words",
  "definition": "50 essential terms for using Git and version control systems to manage source code.",
  "words": [
    { "word": "Commit", "pronunciation": "/kə-MIT/", "meaning": "A saved snapshot of changes in a version control system.", "sentence": "I made a commit with the message 'fix login bug'." },
    { "word": "Clone", "pronunciation": "/KLOHN/", "meaning": "Creating a local copy of a remote repository.", "sentence": "I cloned the repository to start working on it locally." },
    { "word": "Push (Git)", "pronunciation": "/PUSH/", "meaning": "Uploading local commits to a remote repository.", "sentence": "Don't forget to push your changes before ending the day." },
    { "word": "Pull (Git)", "pronunciation": "/PUL/", "meaning": "Downloading and merging changes from a remote repository.", "sentence": "Pull the latest changes before starting new work." },
    { "word": "Fetch (Git)", "pronunciation": "/FECH/", "meaning": "Downloading updates from a remote repository without merging them.", "sentence": "I fetched the latest changes to see what's new before merging." },
    { "word": "Fork (Git)", "pronunciation": "/FORK/", "meaning": "A personal copy of someone else's repository.", "sentence": "I forked the open-source project to contribute a fix." },
    { "word": "Staging area", "pronunciation": "", "meaning": "A space where changes are prepared before being committed.", "sentence": "Add these files to the staging area before committing." },
    { "word": "Commit history", "pronunciation": "", "meaning": "The chronological record of all commits made to a repository.", "sentence": "I checked the commit history to see who made that change." },
    { "word": "HEAD (Git)", "pronunciation": "/HED/", "meaning": "A reference pointing to the current commit in a Git repository.", "sentence": "HEAD is currently pointing to the latest commit on main." },
    { "word": "Checkout", "pronunciation": "/CHEK-owt/", "meaning": "Switching to a different branch or commit in a repository.", "sentence": "I checked out the feature branch to review the changes." },
    { "word": "Rebase", "pronunciation": "/REE-bays/", "meaning": "Reapplying commits on top of another base branch.", "sentence": "We rebased our branch onto main to include the latest changes." },
    { "word": "Cherry-pick", "pronunciation": "/CHER-ee-pik/", "meaning": "Applying a specific commit from one branch onto another.", "sentence": "I cherry-picked the bug fix into the release branch." },
    { "word": "Tag (Git)", "pronunciation": "/TAG/", "meaning": "A marker used to label a specific point in commit history, often a release.", "sentence": "We tagged this commit as version 2.0." },
    { "word": "Remote (Git)", "pronunciation": "", "meaning": "A version of a repository hosted elsewhere, like on GitHub.", "sentence": "We pushed the changes to the remote repository." },
    { "word": "Origin (Git)", "pronunciation": "", "meaning": "The default name for the remote repository a project was cloned from.", "sentence": "Push your changes to origin main." },
    { "word": "Diff", "pronunciation": "/DIF/", "meaning": "A comparison showing the differences between two versions of a file.", "sentence": "Check the diff to see exactly what changed in this commit." },
    { "word": "Stash", "pronunciation": "/STASH/", "meaning": "Temporarily saving uncommitted changes to work on something else.", "sentence": "I stashed my changes to quickly fix an urgent bug." },
    { "word": "Merge conflict", "pronunciation": "", "meaning": "A situation where Git can't automatically combine changes from two branches.", "sentence": "I had to manually resolve a merge conflict in this file." },
    { "word": "Git blame", "pronunciation": "", "meaning": "A command showing who last modified each line of a file.", "sentence": "I used git blame to find out who introduced this bug." },
    { "word": "Git log", "pronunciation": "", "meaning": "A command displaying the commit history of a repository.", "sentence": "Run git log to see recent commits and their messages." },
    { "word": "Fast-forward merge", "pronunciation": "", "meaning": "A merge where the target branch simply moves forward, with no new commit.", "sentence": "Since there were no conflicting changes, Git performed a fast-forward merge." },
    { "word": "Squash (Git)", "pronunciation": "/SKWOSH/", "meaning": "Combining multiple commits into a single commit.", "sentence": "We squashed our commits into one before merging to main." },
    { "word": "Detached HEAD", "pronunciation": "", "meaning": "A state where HEAD points directly to a commit instead of a branch.", "sentence": "I accidentally entered a detached HEAD state while checking out an old commit." },
    { "word": "Upstream (Git)", "pronunciation": "", "meaning": "The original repository a fork was created from.", "sentence": "I synced my fork with the upstream repository." },
    { "word": ".gitignore", "pronunciation": "", "meaning": "A file specifying which files Git should not track.", "sentence": "We added the node_modules folder to .gitignore." },
    { "word": "Git hook", "pronunciation": "", "meaning": "A script that runs automatically at specific points in the Git workflow.", "sentence": "A pre-commit git hook runs the linter before allowing a commit." },
    { "word": "Submodule (Git)", "pronunciation": "", "meaning": "A repository embedded inside another repository.", "sentence": "This shared library is included as a Git submodule." },
    { "word": "Reflog", "pronunciation": "/REF-log/", "meaning": "A record of updates to branch tips, useful for recovering lost commits.", "sentence": "I used reflog to recover a commit after an accidental reset." },
    { "word": "Force push", "pronunciation": "", "meaning": "Overwriting remote history with local changes, potentially losing commits.", "sentence": "Be careful with a force push, it can overwrite others' work." },
    { "word": "Bisect (Git)", "pronunciation": "/by-SEKT/", "meaning": "A binary search technique to find the commit that introduced a bug.", "sentence": "We used git bisect to find exactly which commit broke the build." },
    { "word": "Working directory (Git)", "pronunciation": "", "meaning": "The local folder containing a project's files with any uncommitted changes.", "sentence": "You have uncommitted changes in your working directory." },
    { "word": "Pull request review", "pronunciation": "", "meaning": "The process of examining proposed changes before merging them.", "sentence": "The pull request review flagged a missing test case." },
    { "word": "Trunk-based development", "pronunciation": "", "meaning": "A workflow where developers merge small changes frequently into a shared main branch.", "sentence": "Trunk-based development keeps our main branch always deployable." },
    { "word": "Feature branch", "pronunciation": "", "meaning": "A branch created specifically to develop a single feature.", "sentence": "I created a feature branch to build the new search functionality." },
    { "word": "Git workflow", "pronunciation": "", "meaning": "An agreed-upon pattern for using branches and merges in a team.", "sentence": "Our Git workflow requires a review before merging to main." },
    { "word": "Amend (Git)", "pronunciation": "/ə-MEND/", "meaning": "Modifying the most recent commit instead of creating a new one.", "sentence": "I amended the commit to fix a typo in the message." },
    { "word": "Git bash", "pronunciation": "", "meaning": "A terminal application providing a Unix-like command line for Git on Windows.", "sentence": "I run my Git commands through Git Bash on my Windows machine." },
    { "word": "Conflict marker", "pronunciation": "", "meaning": "Special symbols Git inserts to show conflicting changes needing resolution.", "sentence": "Remove the conflict markers after resolving the merge conflict." },
    { "word": "Shallow clone", "pronunciation": "", "meaning": "A clone that only includes recent history, not the full repository history.", "sentence": "We used a shallow clone to speed up the CI pipeline." },
    { "word": "Git tag annotation", "pronunciation": "", "meaning": "Extra metadata attached to a Git tag, like a message or author.", "sentence": "We added a Git tag annotation describing the release notes." },
    { "word": "Branch protection", "pronunciation": "", "meaning": "Rules preventing direct changes to important branches without review.", "sentence": "Branch protection requires at least one approval before merging to main." },
    { "word": "Monorepo", "pronunciation": "/MON-oh-reh-poh/", "meaning": "A single repository containing code for multiple projects.", "sentence": "We moved all our services into a single monorepo." },
    { "word": "Polyrepo", "pronunciation": "/POL-ee-reh-poh/", "meaning": "An approach using separate repositories for each project.", "sentence": "We use a polyrepo setup with one repository per microservice." },
    { "word": "Git client", "pronunciation": "", "meaning": "Software used to interact with Git repositories, command-line or graphical.", "sentence": "I prefer a graphical Git client over the command line for visualizing branches." },
    { "word": "Commit message", "pronunciation": "", "meaning": "A short description explaining what changes a commit contains.", "sentence": "Write a clear commit message so others understand your change." },
    { "word": "Rebase conflict", "pronunciation": "", "meaning": "A conflict that occurs while reapplying commits during a rebase.", "sentence": "I had to resolve a rebase conflict before continuing." },
    { "word": "Git ignore pattern", "pronunciation": "", "meaning": "A rule in .gitignore specifying which files or folders to exclude.", "sentence": "We added a git ignore pattern to exclude all .log files." },
    { "word": "Continuous version control", "pronunciation": "", "meaning": "Ongoing use of version control throughout a project's lifecycle.", "sentence": "Continuous version control ensures we never lose track of changes." },
    { "word": "Repository clone URL", "pronunciation": "", "meaning": "The web address used to clone a specific repository.", "sentence": "Copy the repository clone URL from GitHub to get started." },
    { "word": "Git reset", "pronunciation": "", "meaning": "A command that moves the current branch pointer, optionally undoing commits.", "sentence": "I used git reset to undo the last commit before pushing." }
  ],
  "quiz": [
    { "type": "mcq", "question": "What does 'push' do in Git?", "options": ["Uploads local commits to a remote repository", "Downloads changes from a remote", "Deletes a branch", "Creates a new repository"], "answer": "Uploads local commits to a remote repository", "explanation": "Push sends your local commits to the remote repository." },
    { "type": "mcq", "question": "What is a 'merge conflict'?", "options": ["When Git can't automatically combine changes from two branches", "A type of commit message", "A branch protection rule", "A Git command"], "answer": "When Git can't automatically combine changes from two branches", "explanation": "Merge conflicts occur when overlapping changes can't be automatically resolved." },
    { "type": "mcq", "question": "What does 'git blame' show?", "options": ["Who last modified each line of a file", "The commit history", "The current branch name", "Uncommitted changes"], "answer": "Who last modified each line of a file", "explanation": "Git blame attributes each line to the commit and author who last changed it." },
    { "type": "fill", "question": "A ___ is a personal copy of someone else's repository. (Git term)", "answer": "fork", "explanation": "Forking creates your own copy of another repository to work on independently." },
    { "type": "mcq", "question": "What does 'squash' do in Git?", "options": ["Combines multiple commits into one", "Deletes a repository", "Creates a new branch", "Downloads remote changes"], "answer": "Combines multiple commits into one", "explanation": "Squashing merges several commits into a single, cleaner commit." }
  ]
}
